QtBindingHelper
simple_command_launcher_column
