Metadata-Version: 1.1
Name: sclc
Version: 0.3.0
Summary: PySide Widget for executing a list of external system commands
Home-page: https://www.gitorious.org/sclc
Author: Oliver Kurz
Author-email: o.kurz@gmx.de
License: UNKNOWN
Platform: UNKNOWN
Classifier: Programming Language :: Python
Classifier: Programming Language :: Python :: 3
Classifier: Development Status :: 4 - Beta
Classifier: Environment :: Other Environment
Classifier: Intended Audience :: Developers
Classifier: Intended Audience :: System Administrators
Classifier: License :: OSI Approved :: BSD License
Classifier: Operating System :: OS Independent
Classifier: Topic :: Software Development :: Libraries :: Python Modules
